{
  "comparison": {
    "A": {
      "id": "061d064b-1494-4a81-afc5-47ce9f39db86",
      "results": {
        "cost": 131000,
        "timeToMarketMonths": 3,
        "riskScore": 11,
        "complianceGaps": []
      },
      "scenario": {
        "name": "cloud-example",
        "infra": "cloud",
        "costEstimate": 120000,
        "complexity": 1.1,
        "workload": 3,
        "complianceGaps": []
      }
    },
    "B": {
      "id": "61aa65d2-a3e3-44c2-80ee-7803ffbd243b",
      "results": {
        "cost": 139000,
        "timeToMarketMonths": 6,
        "riskScore": 19,
        "complianceGaps": [
          "data residency"
        ]
      },
      "scenario": {
        "name": "hybrid-example",
        "infra": "hybrid",
        "costEstimate": 100000,
        "complexity": 1.4,
        "workload": 4,
        "complianceGaps": [
          "data residency"
        ]
      }
    },
    "recommendation": "Recommend scenario A (061d064b-1494-4a81-afc5-47ce9f39db86) — lower cost and risk.",
    "explanation": {
      "costA": 131000,
      "costB": 139000,
      "riskA": 11,
      "riskB": 19,
      "deltaCost": -8000,
      "deltaRisk": -8
    }
  }
}